zaoxg/VERSION
zaoxg/__init__.py
zaoxg/zaoxg.py
zaoxg-0.0.1.dist-info/LICENSE
zaoxg-0.0.1.dist-info/METADATA
zaoxg-0.0.1.dist-info/WHEEL
zaoxg-0.0.1.dist-info/top_level.txt
zaoxg-0.0.1.dist-info/RECORD
